ai_economist/__init__.py
ai_economist/datasets/__init__.py
ai_economist/datasets/covid19_datasets/__init__.py
ai_economist/datasets/covid19_datasets/us_deaths.py
ai_economist/datasets/covid19_datasets/us_policies.py
ai_economist/datasets/covid19_datasets/us_unemployment.py
ai_economist/datasets/covid19_datasets/us_vaccinations.py
ai_economist/datasets/covid19_datasets/data_and_fitted_params/fitted_params.json
ai_economist/datasets/covid19_datasets/data_and_fitted_params/model_constants.json
ai_economist/datasets/covid19_datasets/data_and_fitted_params/real_world_data.npz
ai_economist/foundation/__init__.py
ai_economist/foundation/env_wrapper.py
ai_economist/foundation/utils.py
ai_economist/foundation/agents/__init__.py
ai_economist/foundation/agents/mobiles.py
ai_economist/foundation/agents/planners.py
ai_economist/foundation/base/__init__.py
ai_economist/foundation/base/base_agent.py
ai_economist/foundation/base/base_component.py
ai_economist/foundation/base/base_env.py
ai_economist/foundation/base/registrar.py
ai_economist/foundation/base/world.py
ai_economist/foundation/components/__init__.py
ai_economist/foundation/components/build.py
ai_economist/foundation/components/continuous_double_auction.py
ai_economist/foundation/components/covid19_components.py
ai_economist/foundation/components/covid19_components_step.cu
ai_economist/foundation/components/move.py
ai_economist/foundation/components/redistribution.py
ai_economist/foundation/components/simple_labor.py
ai_economist/foundation/components/utils.py
ai_economist/foundation/entities/__init__.py
ai_economist/foundation/entities/endogenous.py
ai_economist/foundation/entities/landmarks.py
ai_economist/foundation/entities/resources.py
ai_economist/foundation/scenarios/__init__.py
ai_economist/foundation/scenarios/covid19/__init__.py
ai_economist/foundation/scenarios/covid19/covid19_build.cu
ai_economist/foundation/scenarios/covid19/covid19_env.py
ai_economist/foundation/scenarios/covid19/covid19_env_step.cu
ai_economist-1.7.1.dist-info/LICENSE.txt
ai_economist-1.7.1.dist-info/METADATA
ai_economist-1.7.1.dist-info/WHEEL
ai_economist-1.7.1.dist-info/top_level.txt
ai_economist-1.7.1.dist-info/RECORD
