Metadata-Version: 2.1
Name: ai-economist
Version: 1.7.1
Summary: Foundation: An Economics Simulation Framework
Home-page: https://github.com/salesforce/ai-economist
Author: Stephan Zheng, Alex Trott, Sunil Srinivasa
Author-email: stephan.zheng@salesforce.com
License: UNKNOWN
Platform: UNKNOWN
Classifier: Programming Language :: Python :: 3
Classifier: License :: OSI Approved :: BSD License
Classifier: Operating System :: OS Independent
Requires-Python: >=3.7
Requires-Dist: appdirs (==1.4.4)
Requires-Dist: appnope (==0.1.2)
Requires-Dist: argon2-cffi (==20.1.0)
Requires-Dist: astroid (==2.5.6)
Requires-Dist: async-generator (==1.10)
Requires-Dist: attrs (==21.2.0)
Requires-Dist: backcall (==0.2.0)
Requires-Dist: beautifulsoup4 (==4.9.3)
Requires-Dist: black (==21.5b1)
Requires-Dist: bleach (==3.3.0)
Requires-Dist: bs4 (==0.0.1)
Requires-Dist: certifi (==2020.12.5)
Requires-Dist: cffi (==1.14.5)
Requires-Dist: chardet (==4.0.0)
Requires-Dist: click (==8.0.1)
Requires-Dist: cycler (==0.10.0)
Requires-Dist: decorator (==5.0.9)
Requires-Dist: defusedxml (==0.7.1)
Requires-Dist: entrypoints (==0.3)
Requires-Dist: et-xmlfile (==1.1.0)
Requires-Dist: flake8 (==3.9.2)
Requires-Dist: GPUtil (==1.4.0)
Requires-Dist: idna (==2.10)
Requires-Dist: iniconfig (==1.1.1)
Requires-Dist: ipykernel (==5.5.5)
Requires-Dist: ipython (==7.31.1)
Requires-Dist: ipython-genutils (==0.2.0)
Requires-Dist: ipywidgets (==7.6.3)
Requires-Dist: isort (==5.8.0)
Requires-Dist: jedi (==0.18.0)
Requires-Dist: Jinja2 (==3.0.1)
Requires-Dist: jsonschema (==3.2.0)
Requires-Dist: jupyter (==1.0.0)
Requires-Dist: jupyter-client (==6.1.12)
Requires-Dist: jupyter-console (==6.4.0)
Requires-Dist: jupyter-core (==4.7.1)
Requires-Dist: jupyterlab-pygments (==0.1.2)
Requires-Dist: jupyterlab-widgets (==1.0.0)
Requires-Dist: kiwisolver (==1.3.1)
Requires-Dist: lazy-object-proxy (==1.6.0)
Requires-Dist: lz4 (==3.1.3)
Requires-Dist: MarkupSafe (==2.0.1)
Requires-Dist: matplotlib (==3.2.1)
Requires-Dist: matplotlib-inline (==0.1.2)
Requires-Dist: mccabe (==0.6.1)
Requires-Dist: mistune (==0.8.4)
Requires-Dist: mypy-extensions (==0.4.3)
Requires-Dist: nbclient (==0.5.3)
Requires-Dist: nbconvert (==6.0.7)
Requires-Dist: nbformat (==5.1.3)
Requires-Dist: nest-asyncio (==1.5.1)
Requires-Dist: notebook (==6.4.1)
Requires-Dist: numpy (==1.21.0)
Requires-Dist: openpyxl (==3.0.7)
Requires-Dist: packaging (==20.9)
Requires-Dist: pandas (==1.2.4)
Requires-Dist: pandocfilters (==1.4.3)
Requires-Dist: parso (==0.8.2)
Requires-Dist: pathspec (==0.8.1)
Requires-Dist: pexpect (==4.8.0)
Requires-Dist: pickleshare (==0.7.5)
Requires-Dist: Pillow (==9.0.0)
Requires-Dist: pluggy (==0.13.1)
Requires-Dist: prometheus-client (==0.10.1)
Requires-Dist: prompt-toolkit (==3.0.18)
Requires-Dist: ptyprocess (==0.7.0)
Requires-Dist: py (==1.10.0)
Requires-Dist: pycodestyle (==2.7.0)
Requires-Dist: pycparser (==2.20)
Requires-Dist: pycryptodome (==3.10.1)
Requires-Dist: pyflakes (==2.3.1)
Requires-Dist: Pygments (==2.9.0)
Requires-Dist: pylint (==2.8.2)
Requires-Dist: pyparsing (==2.4.7)
Requires-Dist: pyrsistent (==0.17.3)
Requires-Dist: pytest (==6.2.4)
Requires-Dist: python-dateutil (==2.8.1)
Requires-Dist: pytz (==2021.1)
Requires-Dist: pyyaml (==5.4.1)
Requires-Dist: pyzmq (==22.0.3)
Requires-Dist: qtconsole (==5.1.0)
Requires-Dist: QtPy (==1.9.0)
Requires-Dist: regex (==2021.4.4)
Requires-Dist: requests (==2.25.1)
Requires-Dist: scipy (==1.6.3)
Requires-Dist: Send2Trash (==1.5.0)
Requires-Dist: six (==1.16.0)
Requires-Dist: soupsieve (==2.2.1)
Requires-Dist: terminado (==0.10.0)
Requires-Dist: testpath (==0.5.0)
Requires-Dist: toml (==0.10.2)
Requires-Dist: tornado (==6.1)
Requires-Dist: tqdm (==4.60.0)
Requires-Dist: traitlets (==5.0.5)
Requires-Dist: typing-extensions (==3.10.0.0)
Requires-Dist: urllib3 (==1.26.5)
Requires-Dist: wcwidth (==0.2.5)
Requires-Dist: webencodings (==0.5.1)
Requires-Dist: widgetsnbextension (==3.5.1)
Requires-Dist: wrapt (==1.12.1)
